PlvLogger/__init__.py
PlvLogger/logger.py
PlvLogger-0.166.dist-info/METADATA
PlvLogger-0.166.dist-info/WHEEL
PlvLogger-0.166.dist-info/top_level.txt
PlvLogger-0.166.dist-info/RECORD
