Metadata-Version: 2.1
Name: PlvLogger
Version: 0.166
Summary: add Singleton
Home-page: https://github.com/plv88/MyLogger
Author: plv88
Author-email: plv.andrey88@gmail.com
Classifier: Programming Language :: Python :: 3
Classifier: Operating System :: OS Independent
Requires-Python: >=3.10
